README.md
setup.py
flickerprint/__init__.py
flickerprint/version.py
flickerprint.egg-info/PKG-INFO
flickerprint.egg-info/SOURCES.txt
flickerprint.egg-info/dependency_links.txt
flickerprint.egg-info/entry_points.txt
flickerprint.egg-info/requires.txt
flickerprint.egg-info/top_level.txt
flickerprint/analysis/__init__.py
flickerprint/analysis/cli_analysis.py
flickerprint/analysis/plotting.py
flickerprint/analysis/statistics.py
flickerprint/analysis/gui/__init__.py
flickerprint/analysis/gui/app.py
flickerprint/analysis/gui/modules/__init__.py
flickerprint/analysis/gui/modules/file_upload_module.py
flickerprint/analysis/gui/modules/graph_module.py
flickerprint/analysis/gui/modules/stats_module.py
flickerprint/analysis/gui/plotting_tools/__init__.py
flickerprint/analysis/gui/plotting_tools/create_plot.py
flickerprint/common/__init__.py
flickerprint/common/boundary_extraction.py
flickerprint/common/configuration.py
flickerprint/common/create_project_dir.py
flickerprint/common/defaults.yaml
flickerprint/common/frame_gen.py
flickerprint/common/granule_locator.py
flickerprint/common/kernels.py
flickerprint/common/utilities.py
flickerprint/fluctuation/__init__.py
flickerprint/fluctuation/spectra.py
flickerprint/tools/plot_tools.py
flickerprint/workflow/__init__.py
flickerprint/workflow/bayesian_optimisation.py
flickerprint/workflow/extract_physical_values.py
flickerprint/workflow/manager.py
flickerprint/workflow/process_image.py
flickerprint/workflow/process_txt.py