Metadata-Version: 2.4
Name: flickerprint
Version: 1.0
Summary: FlickerPrint: Non-invasive measurement of biomolecular condensate mechanical properties from confocal microscopy images.
Author: Carl Jones, Jack Law, Thomas Williamson, Fynn Wolf, Endre Tønnessen
Maintainer: Thomas Williamson
Project-URL: Documentation, https://flickerprint.github.io/FlickerPrint/
Project-URL: Source, https://github.com/FlickerPrint/FlickerPrint
Requires-Python: >=3.9, <3.12
Requires-Dist: numpy
Requires-Dist: python-javabridge>=4.0.4
Requires-Dist: python-bioformats>=4.1.0
Requires-Dist: matplotlib
Requires-Dist: scikit-image
Requires-Dist: pandas
Requires-Dist: seaborn
Requires-Dist: h5py>=3.11.1
Requires-Dist: tqdm
Requires-Dist: argh
Requires-Dist: wget
Requires-Dist: strictyaml>=1.7.3
Requires-Dist: tables>=3.9.1
Requires-Dist: opencv-python>=4.10.0.84
Requires-Dist: exifread>=3.0.0
Requires-Dist: tensorflow>=2.16.2
Requires-Dist: shiny==1.2.1
Requires-Dist: trieste
Requires-Dist: shinyswatch
Requires-Dist: jinja2
Requires-Dist: cmake
Dynamic: author
Dynamic: description
Dynamic: description-content-type
Dynamic: maintainer
Dynamic: project-url
Dynamic: requires-dist
Dynamic: requires-python
Dynamic: summary
